suntimes/__init__.py
suntimes/suntimes.py
suntimes-1.1.2.dist-info/LICENSE
suntimes-1.1.2.dist-info/METADATA
suntimes-1.1.2.dist-info/WHEEL
suntimes-1.1.2.dist-info/top_level.txt
suntimes-1.1.2.dist-info/RECORD
