Metadata-Version: 2.1
Name: suntimes
Version: 1.1.2
Summary: For a given place (longitude, latitude and altitude) and a given day, returns the time of sunrise and the time of sunset (in UTC and in local time). Create and save a json or csv file with the timetables for a whole year. Calculations valid beyond the polar circles; returns Polar Day or Polar Night if needed.
Author-email: Paul MATHIS <pmathis@protonmail.com>
License: MIT License        
Project-URL: Homepage, https://github.com/p-mathis/suntimes
Keywords: sun,sunset,sunrise,python
Classifier: Programming Language :: Python :: 3
Classifier: License :: OSI Approved :: MIT License
Classifier: Operating System :: OS Independent
Requires-Python: >=3.6
License-File: LICENSE
Requires-Dist: pytz
Requires-Dist: tzlocal
Requires-Dist: jdcal
